{
  "timestamp": "2025-12-16T05:25:21.572996",
  "feature_mapping": {
    "Dashboard": {
      "expected_endpoints": [
        "/api/admin/dashboard",
        "/api/admin/platform-stats",
        "/api/admin/analytics"
      ],
      "found_endpoints": [
        "/api/admin/dashboard",
        "/api/admin/platform-stats",
        "/api/admin/analytics"
      ],
      "missing_endpoints": [],
      "coverage": 100.0
    },
    "UserManagement": {
      "expected_endpoints": [
        "/api/admin/users",
        "/api/users",
        "/api/admin/users/{user_id}/performance",
        "/api/admin/users/bulk-update",
        "/api/admin/registrations",
        "/api/admin/registrations/{registration_id}/approve"
      ],
      "found_endpoints": [
        "/api/admin/users",
        "/api/users",
        "/api/admin/users/{user_id}/performance",
        "/api/admin/users/bulk-update",
        "/api/admin/registrations",
        "/api/admin/registrations/{registration_id}/approve"
      ],
      "missing_endpoints": [],
      "coverage": 100.0
    },
    "OpexTradingManagement": {
      "expected_endpoints": [
        "/api/admin/trading",
        "/api/admin/trading/adjustments",
        "/api/admin/trades",
        "/api/admin/trades/{trade_id}/approve",
        "/api/admin/trades/{trade_id}/reject"
      ],
      "found_endpoints": [
        "/api/admin/trading",
        "/api/admin/trading/adjustments",
        "/api/admin/trades",
        "/api/admin/trades/{trade_id}/approve",
        "/api/admin/trades/{trade_id}/reject"
      ],
      "missing_endpoints": [],
      "coverage": 100.0
    },
    "FinancialManagement": {
      "expected_endpoints": [
        "/api/admin/deposits",
        "/api/admin/deposits/{deposit_id}",
        "/api/admin/deposits/{deposit_id}/approve",
        "/api/admin/deposits/{deposit_id}/reject",
        "/api/admin/withdrawals",
        "/api/admin/withdrawals/{withdrawal_id}",
        "/api/admin/withdrawals/{withdrawal_id}/approve",
        "/api/admin/withdrawals/{withdrawal_id}/reject",
        "/api/admin/invoices",
        "/api/admin/invoices/{invoice_id}",
        "/api/admin/payments",
        "/api/admin/payments/{payment_id}"
      ],
      "found_endpoints": [
        "/api/admin/deposits",
        "/api/admin/deposits/{deposit_id}",
        "/api/admin/deposits/{deposit_id}/approve",
        "/api/admin/deposits/{deposit_id}/reject",
        "/api/admin/withdrawals",
        "/api/admin/withdrawals/{withdrawal_id}",
        "/api/admin/withdrawals/{withdrawal_id}/approve",
        "/api/admin/withdrawals/{withdrawal_id}/reject",
        "/api/admin/invoices",
        "/api/admin/invoices/{invoice_id}",
        "/api/admin/payments",
        "/api/admin/payments/{payment_id}"
      ],
      "missing_endpoints": [],
      "coverage": 100.0
    },
    "AnalyticsReports": {
      "expected_endpoints": [
        "/api/admin/analytics",
        "/api/admin/analytics/performance",
        "/api/admin/reports",
        "/api/admin/reports/scheduled",
        "/api/admin/platform-stats"
      ],
      "found_endpoints": [
        "/api/admin/analytics",
        "/api/admin/analytics/performance",
        "/api/admin/reports",
        "/api/admin/reports/scheduled",
        "/api/admin/platform-stats"
      ],
      "missing_endpoints": [],
      "coverage": 100.0
    },
    "SystemSettings": {
      "expected_endpoints": [
        "/api/admin/settings",
        "/api/admin/settings/market-display",
        "/api/admin/settings/chart-display",
        "/api/admin/settings/market-scenarios",
        "/api/admin/settings/registration-fields",
        "/api/admin/settings/cors-origins",
        "/api/admin/settings/auto-approve-registration"
      ],
      "found_endpoints": [
        "/api/admin/settings",
        "/api/admin/settings/market-display",
        "/api/admin/settings/chart-display",
        "/api/admin/settings/market-scenarios",
        "/api/admin/settings/registration-fields",
        "/api/admin/settings/cors-origins",
        "/api/admin/settings/auto-approve-registration"
      ],
      "missing_endpoints": [],
      "coverage": 100.0
    },
    "AdminTradingControls": {
      "expected_endpoints": [
        "/api/admin/trading/orders/{order_id}",
        "/api/admin/trading/orders/{order_id}/force",
        "/api/admin/trading/positions/{position_id}",
        "/api/admin/trading/positions/{position_id}/force-close",
        "/api/admin/trading/prices/{symbol}",
        "/api/admin/trading/balances/{user_id}",
        "/api/admin/trading-adjustments/win-rate",
        "/api/admin/trading-adjustments/position-override"
      ],
      "found_endpoints": [
        "/api/admin/trading/orders/{order_id}",
        "/api/admin/trading/orders/{order_id}/force",
        "/api/admin/trading/positions/{position_id}",
        "/api/admin/trading/positions/{position_id}/force-close",
        "/api/admin/trading/prices/{symbol}",
        "/api/admin/trading/balances/{user_id}",
        "/api/admin/trading-adjustments/win-rate",
        "/api/admin/trading-adjustments/position-override"
      ],
      "missing_endpoints": [],
      "coverage": 100.0
    },
    "DiagnosticsManagement": {
      "expected_endpoints": [
        "/api/diagnostics/trading-report",
        "/api/diagnostics/trading-reports",
        "/api/diagnostics/trading-reports/{report_id}"
      ],
      "found_endpoints": [
        "/api/diagnostics/trading-report",
        "/api/diagnostics/trading-reports",
        "/api/diagnostics/trading-reports/{report_id}"
      ],
      "missing_endpoints": [],
      "coverage": 100.0
    },
    "AlertManagement": {
      "expected_endpoints": [
        "/api/alert-rules",
        "/api/alert-rules/{rule_id}",
        "/api/alert-history",
        "/api/alert-history/{alert_id}/acknowledge",
        "/api/alert-history/{alert_id}/resolve"
      ],
      "found_endpoints": [
        "/api/alert-rules",
        "/api/alert-rules/{rule_id}",
        "/api/alert-history",
        "/api/alert-history/{alert_id}/acknowledge",
        "/api/alert-history/{alert_id}/resolve"
      ],
      "missing_endpoints": [],
      "coverage": 100.0
    },
    "ScenarioBuilder": {
      "expected_endpoints": [
        "/api/admin/simulator/sessions",
        "/api/admin/simulator/sessions/start",
        "/api/admin/simulator/sessions/stop",
        "/api/admin/simulator/sessions/reset",
        "/api/admin/simulator/sessions/replay",
        "/api/admin/simulator/monitoring"
      ],
      "found_endpoints": [
        "/api/admin/simulator/sessions",
        "/api/admin/simulator/sessions/start",
        "/api/admin/simulator/sessions/stop",
        "/api/admin/simulator/sessions/reset",
        "/api/admin/simulator/sessions/replay",
        "/api/admin/simulator/monitoring"
      ],
      "missing_endpoints": [],
      "coverage": 100.0
    },
    "MarketPreview": {
      "expected_endpoints": [
        "/api/admin/market-preview",
        "/api/admin/market-preview/{symbol}"
      ],
      "found_endpoints": [
        "/api/admin/market-preview",
        "/api/admin/market-preview/{symbol}"
      ],
      "missing_endpoints": [],
      "coverage": 100.0
    },
    "EducationalHub": {
      "expected_endpoints": [
        "/api/education/videos",
        "/api/education/ebooks",
        "/api/education/calendar",
        "/api/education/reports"
      ],
      "found_endpoints": [
        "/api/education/videos",
        "/api/education/ebooks",
        "/api/education/calendar",
        "/api/education/reports"
      ],
      "missing_endpoints": [],
      "coverage": 100.0
    },
    "AuditLogViewer": {
      "expected_endpoints": [
        "/api/logs",
        "/api/logs/stats",
        "/api/logs/{log_id}",
        "/api/compliance/audit"
      ],
      "found_endpoints": [
        "/api/logs",
        "/api/logs/stats",
        "/api/logs/{log_id}",
        "/api/compliance/audit"
      ],
      "missing_endpoints": [],
      "coverage": 100.0
    }
  },
  "service_api_calls": {
    "admin_trading.js": [
      "/api/admin/trading"
    ],
    "api.js": [
      "/api/admin/customers/wallet-balances",
      "/api/admin/settings/registration-fields"
    ],
    "auth.js": [
      "/api/auth/login",
      "/api/auth/logout",
      "/api/auth/refresh"
    ]
  },
  "service_endpoint_status": {
    "/api/admin/customers/wallet-balances": true,
    "/api/admin/settings/registration-fields": true,
    "/api/admin/trading": true,
    "/api/auth/login": false,
    "/api/auth/logout": true,
    "/api/auth/refresh": true
  },
  "summary": {
    "total_features": 13,
    "features_with_full_coverage": 13,
    "service_files": 3,
    "unique_service_endpoints": 6
  }
}